cusingler/cusingler.cp38-win_amd64.pyd
cusingler-1.1.0.dist-info/LICENSE
cusingler-1.1.0.dist-info/METADATA
cusingler-1.1.0.dist-info/WHEEL
cusingler-1.1.0.dist-info/top_level.txt
cusingler-1.1.0.dist-info/RECORD
