Metadata-Version: 2.1
Name: cusingler
Version: 1.1.0
Summary: Accelerate cell annotation in SingleR by GPU
Home-page: https://github.com/STOmics/cusingler
Author: zhaofuxiang
Author-email: zhaofuxiang@stomics.tech
Classifier: Programming Language :: Python :: 3
Classifier: License :: OSI Approved :: MIT License
Classifier: Operating System :: OS Independent
Requires-Python: >=3.7
License-File: LICENSE
Requires-Dist: h5py
Provides-Extra: test
Requires-Dist: pytest >=6.0 ; extra == 'test'
